Metadata-Version: 2.1
Name: torch-position-embedding
Version: 0.8.0
Summary: Position embedding implemented in PyTorch
Home-page: https://github.com/CyberZHG/torch-position-embedding
Author: CyberZHG
Author-email: CyberZHG@users.noreply.github.com
License: MIT
Platform: UNKNOWN
Classifier: Programming Language :: Python :: 3
Classifier: License :: OSI Approved :: MIT License
Classifier: Operating System :: OS Independent
